zippyshare_generator/__init__.py
zippyshare_generator/__main__.py
zippyshare_generator/__version__.py
zippyshare_generator/js_exe.py
zippyshare_generator/zippyshare.ini
zippyshare_generator/zippyshare.py
zippyshare_generator-0.29.data/data/LICENSE.rst
zippyshare_generator-0.29.data/data/README.rst
zippyshare_generator-0.29.data/data/__version__.py
zippyshare_generator-0.29.data/data/zippyshare.ini
zippyshare_generator-0.29.dist-info/DESCRIPTION.rst
zippyshare_generator-0.29.dist-info/LICENSE.txt
zippyshare_generator-0.29.dist-info/METADATA
zippyshare_generator-0.29.dist-info/RECORD
zippyshare_generator-0.29.dist-info/WHEEL
zippyshare_generator-0.29.dist-info/entry_points.txt
zippyshare_generator-0.29.dist-info/metadata.json
zippyshare_generator-0.29.dist-info/top_level.txt
