Metadata-Version: 2.0
Name: zippyshare-generator
Version: 0.29
Summary: Generator Zippyshare Links
Home-page: https://bitbucket.org/licface/zippyshare_generator
Author: cumulus13 Team
Author-email: cumulus13@gmail.com
License: BSD
Platform: UNKNOWN
Classifier: Development Status :: 5 - Production/Stable
Classifier: Intended Audience :: Developers
Classifier: License :: OSI Approved :: BSD License
Classifier: Operating System :: OS Independent
Classifier: Programming Language :: Python
Classifier: Programming Language :: Python :: 2
Classifier: Programming Language :: Python :: 2.7
Requires-Python: >=2.7, !=3.0.*, !=3.1.*, !=3.2.*, !=3.3.*
Requires-Dist: argparse
Requires-Dist: bs4
Requires-Dist: clipboard
Requires-Dist: configparser
Requires-Dist: configset
Requires-Dist: idm
Requires-Dist: js2py
Requires-Dist: make-colors (>=3.12)
Requires-Dist: parserheader
Requires-Dist: pydebugger
Requires-Dist: pywget
Requires-Dist: requests
